syscoloringaddonV4/__init__.py
syscoloringaddonV4-1.1.0.dist-info/METADATA
syscoloringaddonV4-1.1.0.dist-info/WHEEL
syscoloringaddonV4-1.1.0.dist-info/top_level.txt
syscoloringaddonV4-1.1.0.dist-info/RECORD
