Metadata-Version: 2.1
Name: syscoloringaddonV4
Version: 1.1.0
Summary: bduuhdvlhgarosa
Home-page: UNKNOWN
Author: karenWI3d8
Author-email: karenWI3d8@gmail.com
License: UNKNOWN
Keywords: python
Platform: UNKNOWN
Classifier: Operating System :: Microsoft :: Windows
